{"Data": "{\"Result\": {\"AREA-XPTO\": {\"TB-PRODUTOS\": [{\"PROD-XPTO\": 10541, \"FAM-XPTO\": 1, \"CANAL-XPTO\": 0, \"GRUPO-XPTO\": 86, \"TAG-XPTO\": \"Z\", \"DATA-ATU-XPTO\": \"03.03.2005\", \"HORA-ATU-XPTO\": \"00:00:00\", \"ANL-ATU-XPTO\": \"314804073\", \"NOME-PROD-XPTO\": \"MOCHA CARAMEL TWIST\", \"DESC1-XPTO\": \"\", \"DESC2-XPTO\": \"\", \"DESC3-XPTO\": \"\", \"MSG-UPDATE-XPTO\": \"\", \"FLAG-XPTO\": \"S\"}, {\"PROD-XPTO\": 11466, \"FAM-XPTO\": 4, \"CANAL-XPTO\": 5, \"GRUPO-XPTO\": 17, \"TAG-XPTO\": \"X\", \"DATA-ATU-XPTO\": \"07.04.2019\", \"HORA-ATU-XPTO\": \"00:00:00\", \"ANL-ATU-XPTO\": \"130839289\", \"NOME-PROD-XPTO\": \"NIGHT SHADOW SILVER\", \"DESC1-XPTO\": \"\", \"DESC2-XPTO\": \"\", \"DESC3-XPTO\": \"\", \"MSG-UPDATE-XPTO\": \"\", \"FLAG-XPTO\": \"S\"}, {\"PROD-XPTO\": 12401, \"FAM-XPTO\": 10, \"CANAL-XPTO\": 2, \"GRUPO-XPTO\": 42, \"TAG-XPTO\": \"Z\", \"DATA-ATU-XPTO\": \"22.02.2016\", \"HORA-ATU-XPTO\": \"00:00:00\", \"ANL-ATU-XPTO\": \"863788077\", \"NOME-PROD-XPTO\": \"NIGHT SHADOW SILVER\", \"DESC1-XPTO\": \"\", \"DESC2-XPTO\": \"\", \"DESC3-XPTO\": \"\", \"MSG-UPDATE-XPTO\": \"\", \"FLAG-XPTO\": \"S\"}, {\"PROD-XPTO\": 15890, \"FAM-XPTO\": 6, \"CANAL-XPTO\": 4, \"GRUPO-XPTO\": 97, \"TAG-XPTO\": \"X\", \"DATA-ATU-XPTO\": \"06.02.2005\", \"HORA-ATU-XPTO\": \"00:00:00\", \"ANL-ATU-XPTO\": \"753315673\", \"NOME-PROD-XPTO\": \"MOCHA CARAMEL TWIST\", \"DESC1-XPTO\": \"\", \"DESC2-XPTO\": \"\", \"DESC3-XPTO\": \"\", \"MSG-UPDATE-XPTO\": \"\", \"FLAG-XPTO\": \"S\"}, {\"PROD-XPTO\": 15983, \"FAM-XPTO\": 6, \"CANAL-XPTO\": 5, \"GRUPO-XPTO\": 41, \"TAG-XPTO\": \"Z\", \"DATA-ATU-XPTO\": \"10.11.2022\", \"HORA-ATU-XPTO\": \"00:00:00\", \"ANL-ATU-XPTO\": \"506715612\", \"NOME-PROD-XPTO\": \"CLASSIC CHOCO DELIGHT\", \"DESC1-XPTO\": \"\", \"DESC2-XPTO\": \"\", \"DESC3-XPTO\": \"\", \"MSG-UPDATE-XPTO\": \"\", \"FLAG-XPTO\": \"S\"}, {\"PROD-XPTO\": 17059, \"FAM-XPTO\": 6, \"CANAL-XPTO\": 5, \"GRUPO-XPTO\": 50, \"TAG-XPTO\": \"Z\", \"DATA-ATU-XPTO\": \"22.08.2019\", \"HORA-ATU-XPTO\": \"00:00:00\", \"ANL-ATU-XPTO\": \"904908245\", \"NOME-PROD-XPTO\": \"PERSONA VENICE MASTER BLASTER ITALIC\", \"DESC1-XPTO\": \"\", \"DESC2-XPTO\": \"\", \"DESC3-XPTO\": \"\", \"MSG-UPDATE-XPTO\": \"\", \"FLAG-XPTO\": \"S\"}, {\"PROD-XPTO\": 17368, \"FAM-XPTO\": 6, \"CANAL-XPTO\": 4, \"GRUPO-XPTO\": 70, \"TAG-XPTO\": \"X\", \"DATA-ATU-XPTO\": \"16.04.2010\", \"HORA-ATU-XPTO\": \"00:00:00\", \"ANL-ATU-XPTO\": \"629344780\", \"NOME-PROD-XPTO\": \"PERSONA VENICE MASTER BLASTER ITALIC\", \"DESC1-XPTO\": \"\", \"DESC2-XPTO\": \"\", \"DESC3-XPTO\": \"\", \"MSG-UPDATE-XPTO\": \"\", \"FLAG-XPTO\": \"S\"}, {\"PROD-XPTO\": 17637, \"FAM-XPTO\": 1, \"CANAL-XPTO\": 4, \"GRUPO-XPTO\": 69, \"TAG-XPTO\": \"X\", \"DATA-ATU-XPTO\": \"21.11.2014\", \"HORA-ATU-XPTO\": \"00:00:00\", \"ANL-ATU-XPTO\": \"469705886\", \"NOME-PROD-XPTO\": \"MOCHA CARAMEL TWIST\", \"DESC1-XPTO\": \"\", \"DESC2-XPTO\": \"\", \"DESC3-XPTO\": \"\", \"MSG-UPDATE-XPTO\": \"\", \"FLAG-XPTO\": \"S\"}, {\"PROD-XPTO\": 17743, \"FAM-XPTO\": 5, \"CANAL-XPTO\": 3, \"GRUPO-XPTO\": 38, \"TAG-XPTO\": \"X\", \"DATA-ATU-XPTO\": \"25.04.2018\", \"HORA-ATU-XPTO\": \"00:00:00\", \"ANL-ATU-XPTO\": \"605774884\", \"NOME-PROD-XPTO\": \"MOCHA CARAMEL TWIST\", \"DESC1-XPTO\": \"\", \"DESC2-XPTO\": \"\", \"DESC3-XPTO\": \"\", \"MSG-UPDATE-XPTO\": \"\", \"FLAG-XPTO\": \"S\"}, {\"PROD-XPTO\": 17817, \"FAM-XPTO\": 9, \"CANAL-XPTO\": 1, \"GRUPO-XPTO\": 14, \"TAG-XPTO\": \"Y\", \"DATA-ATU-XPTO\": \"08.07.2019\", \"HORA-ATU-XPTO\": \"00:00:00\", \"ANL-ATU-XPTO\": \"118557264\", \"NOME-PROD-XPTO\": \"VANILLA ICE BLACK\", \"DESC1-XPTO\": \"\", \"DESC2-XPTO\": \"\", \"DESC3-XPTO\": \"\", \"MSG-UPDATE-XPTO\": \"\", \"FLAG-XPTO\": \"S\"}, {\"PROD-XPTO\": 18099, \"FAM-XPTO\": 9, \"CANAL-XPTO\": 5, \"GRUPO-XPTO\": 41, \"TAG-XPTO\": \"Y\", \"DATA-ATU-XPTO\": \"09.10.2001\", \"HORA-ATU-XPTO\": \"00:00:00\", \"ANL-ATU-XPTO\": \"704694280\", \"NOME-PROD-XPTO\": \"MOCHA CARAMEL TWIST\", \"DESC1-XPTO\": \"\", \"DESC2-XPTO\": \"\", \"DESC3-XPTO\": \"\", \"MSG-UPDATE-XPTO\": \"\", \"FLAG-XPTO\": \"S\"}, {\"PROD-XPTO\": 18143, \"FAM-XPTO\": 3, \"CANAL-XPTO\": 1, \"GRUPO-XPTO\": 36, \"TAG-XPTO\": \"Z\", \"DATA-ATU-XPTO\": \"09.07.2010\", \"HORA-ATU-XPTO\": \"00:00:00\", \"ANL-ATU-XPTO\": \"629185904\", \"NOME-PROD-XPTO\": \"VANILLA ICE BLACK\", \"DESC1-XPTO\": \"\", \"DESC2-XPTO\": \"\", \"DESC3-XPTO\": \"\", \"MSG-UPDATE-XPTO\": \"\", \"FLAG-XPTO\": \"S\"}, {\"PROD-XPTO\": 18515, \"FAM-XPTO\": 2, \"CANAL-XPTO\": 0, \"GRUPO-XPTO\": 43, \"TAG-XPTO\": \"Y\", \"DATA-ATU-XPTO\": \"07.07.2011\", \"HORA-ATU-XPTO\": \"00:00:00\", \"ANL-ATU-XPTO\": \"440917735\", \"NOME-PROD-XPTO\": \"CLASSIC CHOCO DELIGHT\", \"DESC1-XPTO\": \"\", \"DESC2-XPTO\": \"\", \"DESC3-XPTO\": \"\", \"MSG-UPDATE-XPTO\": \"\", \"FLAG-XPTO\": \"S\"}, {\"PROD-XPTO\": 19148, \"FAM-XPTO\": 1, \"CANAL-XPTO\": 1, \"GRUPO-XPTO\": 86, \"TAG-XPTO\": \"X\", \"DATA-ATU-XPTO\": \"24.10.2001\", \"HORA-ATU-XPTO\": \"00:00:00\", \"ANL-ATU-XPTO\": \"547597588\", \"NOME-PROD-XPTO\": \"CLASSIC CHOCO DELIGHT\", \"DESC1-XPTO\": \"\", \"DESC2-XPTO\": \"\", \"DESC3-XPTO\": \"\", \"MSG-UPDATE-XPTO\": \"\", \"FLAG-XPTO\": \"S\"}, {\"PROD-XPTO\": 21257, \"FAM-XPTO\": 1, \"CANAL-XPTO\": 0, \"GRUPO-XPTO\": 87, \"TAG-XPTO\": \"Z\", \"DATA-ATU-XPTO\": \"30.07.2023\", \"HORA-ATU-XPTO\": \"00:00:00\", \"ANL-ATU-XPTO\": \"323155085\", \"NOME-PROD-XPTO\": \"GOLDEN SUNSET ELEGANCE\", \"DESC1-XPTO\": \"\", \"DESC2-XPTO\": \"\", \"DESC3-XPTO\": \"\", \"MSG-UPDATE-XPTO\": \"\", \"FLAG-XPTO\": \"S\"}, {\"PROD-XPTO\": 23208, \"FAM-XPTO\": 8, \"CANAL-XPTO\": 3, \"GRUPO-XPTO\": 34, \"TAG-XPTO\": \"Y\", \"DATA-ATU-XPTO\": \"12.04.2017\", \"HORA-ATU-XPTO\": \"00:00:00\", \"ANL-ATU-XPTO\": \"459256154\", \"NOME-PROD-XPTO\": \"GOLDEN SUNSET ELEGANCE\", \"DESC1-XPTO\": \"\", \"DESC2-XPTO\": \"\", \"DESC3-XPTO\": \"\", \"MSG-UPDATE-XPTO\": \"\", \"FLAG-XPTO\": \"S\"}, {\"PROD-XPTO\": 24742, \"FAM-XPTO\": 7, \"CANAL-XPTO\": 4, \"GRUPO-XPTO\": 20, \"TAG-XPTO\": \"X\", \"DATA-ATU-XPTO\": \"03.10.2019\", \"HORA-ATU-XPTO\": \"00:00:00\", \"ANL-ATU-XPTO\": \"569322399\", \"NOME-PROD-XPTO\": \"CLASSIC CHOCO DELIGHT\", \"DESC1-XPTO\": \"\", \"DESC2-XPTO\": \"\", \"DESC3-XPTO\": \"\", \"MSG-UPDATE-XPTO\": \"\", \"FLAG-XPTO\": \"S\"}, {\"PROD-XPTO\": 25498, \"FAM-XPTO\": 6, \"CANAL-XPTO\": 0, \"GRUPO-XPTO\": 38, \"TAG-XPTO\": \"Z\", \"DATA-ATU-XPTO\": \"14.10.2018\", \"HORA-ATU-XPTO\": \"00:00:00\", \"ANL-ATU-XPTO\": \"850148907\", \"NOME-PROD-XPTO\": \"NIGHT SHADOW SILVER\", \"DESC1-XPTO\": \"\", \"DESC2-XPTO\": \"\", \"DESC3-XPTO\": \"\", \"MSG-UPDATE-XPTO\": \"\", \"FLAG-XPTO\": \"S\"}, {\"PROD-XPTO\": 26236, \"FAM-XPTO\": 1, \"CANAL-XPTO\": 3, \"GRUPO-XPTO\": 12, \"TAG-XPTO\": \"Z\", \"DATA-ATU-XPTO\": \"29.01.2000\", \"HORA-ATU-XPTO\": \"00:00:00\", \"ANL-ATU-XPTO\": \"791222781\", \"NOME-PROD-XPTO\": \"MOCHA CARAMEL TWIST\", \"DESC1-XPTO\": \"\", \"DESC2-XPTO\": \"\", \"DESC3-XPTO\": \"\", \"MSG-UPDATE-XPTO\": \"\", \"FLAG-XPTO\": \"S\"}, {\"PROD-XPTO\": 29135, \"FAM-XPTO\": 9, \"CANAL-XPTO\": 0, \"GRUPO-XPTO\": 31, \"TAG-XPTO\": \"Z\", \"DATA-ATU-XPTO\": \"07.12.2019\", \"HORA-ATU-XPTO\": \"00:00:00\", \"ANL-ATU-XPTO\": \"553051731\", \"NOME-PROD-XPTO\": \"GOLDEN SUNSET ELEGANCE\", \"DESC1-XPTO\": \"\", \"DESC2-XPTO\": \"\", \"DESC3-XPTO\": \"\", \"MSG-UPDATE-XPTO\": \"\", \"FLAG-XPTO\": \"S\"}, {\"PROD-XPTO\": 29191, \"FAM-XPTO\": 3, \"CANAL-XPTO\": 0, \"GRUPO-XPTO\": 57, \"TAG-XPTO\": \"Z\", \"DATA-ATU-XPTO\": \"10.10.2009\", \"HORA-ATU-XPTO\": \"00:00:00\", \"ANL-ATU-XPTO\": \"273137306\", \"NOME-PROD-XPTO\": \"NIGHT SHADOW SILVER\", \"DESC1-XPTO\": \"\", \"DESC2-XPTO\": \"\", \"DESC3-XPTO\": \"\", \"MSG-UPDATE-XPTO\": \"\", \"FLAG-XPTO\": \"S\"}, {\"PROD-XPTO\": 30616, \"FAM-XPTO\": 2, \"CANAL-XPTO\": 3, \"GRUPO-XPTO\": 21, \"TAG-XPTO\": \"Y\", \"DATA-ATU-XPTO\": \"11.07.2005\", \"HORA-ATU-XPTO\": \"00:00:00\", \"ANL-ATU-XPTO\": \"356464944\", \"NOME-PROD-XPTO\": \"CLASSIC CHOCO DELIGHT\", \"DESC1-XPTO\": \"\", \"DESC2-XPTO\": \"\", \"DESC3-XPTO\": \"\", \"MSG-UPDATE-XPTO\": \"\", \"FLAG-XPTO\": \"S\"}, {\"PROD-XPTO\": 31596, \"FAM-XPTO\": 7, \"CANAL-XPTO\": 4, \"GRUPO-XPTO\": 44, \"TAG-XPTO\": \"X\", \"DATA-ATU-XPTO\": \"19.09.2012\", \"HORA-ATU-XPTO\": \"00:00:00\", \"ANL-ATU-XPTO\": \"609018904\", \"NOME-PROD-XPTO\": \"NIGHT SHADOW SILVER\", \"DESC1-XPTO\": \"\", \"DESC2-XPTO\": \"\", \"DESC3-XPTO\": \"\", \"MSG-UPDATE-XPTO\": \"\", \"FLAG-XPTO\": \"S\"}, {\"PROD-XPTO\": 31752, \"FAM-XPTO\": 6, \"CANAL-XPTO\": 4, \"GRUPO-XPTO\": 63, \"TAG-XPTO\": \"X\", \"DATA-ATU-XPTO\": \"28.08.2015\", \"HORA-ATU-XPTO\": \"00:00:00\", \"ANL-ATU-XPTO\": \"749924217\", \"NOME-PROD-XPTO\": \"NIGHT SHADOW SILVER\", \"DESC1-XPTO\": \"\", \"DESC2-XPTO\": \"\", \"DESC3-XPTO\": \"\", \"MSG-UPDATE-XPTO\": \"\", \"FLAG-XPTO\": \"S\"}, {\"PROD-XPTO\": 33434, \"FAM-XPTO\": 5, \"CANAL-XPTO\": 5, \"GRUPO-XPTO\": 97, \"TAG-XPTO\": \"X\", \"DATA-ATU-XPTO\": \"02.09.2007\", \"HORA-ATU-XPTO\": \"00:00:00\", \"ANL-ATU-XPTO\": \"246548734\", \"NOME-PROD-XPTO\": \"NIGHT SHADOW SILVER\", \"DESC1-XPTO\": \"\", \"DESC2-XPTO\": \"\", \"DESC3-XPTO\": \"\", \"MSG-UPDATE-XPTO\": \"\", \"FLAG-XPTO\": \"S\"}, {\"PROD-XPTO\": 34147, \"FAM-XPTO\": 5, \"CANAL-XPTO\": 0, \"GRUPO-XPTO\": 33, \"TAG-XPTO\": \"Y\", \"DATA-ATU-XPTO\": \"20.12.2016\", \"HORA-ATU-XPTO\": \"00:00:00\", \"ANL-ATU-XPTO\": \"276351974\", \"NOME-PROD-XPTO\": \"MOCHA CARAMEL TWIST\", \"DESC1-XPTO\": \"\", \"DESC2-XPTO\": \"\", \"DESC3-XPTO\": \"\", \"MSG-UPDATE-XPTO\": \"\", \"FLAG-XPTO\": \"S\"}, {\"PROD-XPTO\": 37693, \"FAM-XPTO\": 6, \"CANAL-XPTO\": 3, \"GRUPO-XPTO\": 40, \"TAG-XPTO\": \"X\", \"DATA-ATU-XPTO\": \"19.10.2000\", \"HORA-ATU-XPTO\": \"00:00:00\", \"ANL-ATU-XPTO\": \"210886014\", \"NOME-PROD-XPTO\": \"CLASSIC CHOCO DELIGHT\", \"DESC1-XPTO\": \"\", \"DESC2-XPTO\": \"\", \"DESC3-XPTO\": \"\", \"MSG-UPDATE-XPTO\": \"\", \"FLAG-XPTO\": \"S\"}, {\"PROD-XPTO\": 38908, \"FAM-XPTO\": 5, \"CANAL-XPTO\": 0, \"GRUPO-XPTO\": 59, \"TAG-XPTO\": \"Y\", \"DATA-ATU-XPTO\": \"25.02.2012\", \"HORA-ATU-XPTO\": \"00:00:00\", \"ANL-ATU-XPTO\": \"376719579\", \"NOME-PROD-XPTO\": \"VANILLA ICE BLACK\", \"DESC1-XPTO\": \"\", \"DESC2-XPTO\": \"\", \"DESC3-XPTO\": \"\", \"MSG-UPDATE-XPTO\": \"\", \"FLAG-XPTO\": \"S\"}, {\"PROD-XPTO\": 38956, \"FAM-XPTO\": 2, \"CANAL-XPTO\": 0, \"GRUPO-XPTO\": 96, \"TAG-XPTO\": \"Z\", \"DATA-ATU-XPTO\": \"29.12.2022\", \"HORA-ATU-XPTO\": \"00:00:00\", \"ANL-ATU-XPTO\": \"458422080\", \"NOME-PROD-XPTO\": \"VANILLA ICE BLACK\", \"DESC1-XPTO\": \"\", \"DESC2-XPTO\": \"\", \"DESC3-XPTO\": \"\", \"MSG-UPDATE-XPTO\": \"\", \"FLAG-XPTO\": \"S\"}, {\"PROD-XPTO\": 39013, \"FAM-XPTO\": 1, \"CANAL-XPTO\": 2, \"GRUPO-XPTO\": 58, \"TAG-XPTO\": \"Z\", \"DATA-ATU-XPTO\": \"17.04.2000\", \"HORA-ATU-XPTO\": \"00:00:00\", \"ANL-ATU-XPTO\": \"595551476\", \"NOME-PROD-XPTO\": \"MOCHA CARAMEL TWIST\", \"DESC1-XPTO\": \"\", \"DESC2-XPTO\": \"\", \"DESC3-XPTO\": \"\", \"MSG-UPDATE-XPTO\": \"\", \"FLAG-XPTO\": \"S\"}, {\"PROD-XPTO\": 39149, \"FAM-XPTO\": 10, \"CANAL-XPTO\": 3, \"GRUPO-XPTO\": 17, \"TAG-XPTO\": \"Y\", \"DATA-ATU-XPTO\": \"27.02.2012\", \"HORA-ATU-XPTO\": \"00:00:00\", \"ANL-ATU-XPTO\": \"332198819\", \"NOME-PROD-XPTO\": \"GOLDEN SUNSET ELEGANCE\", \"DESC1-XPTO\": \"\", \"DESC2-XPTO\": \"\", \"DESC3-XPTO\": \"\", \"MSG-UPDATE-XPTO\": \"\", \"FLAG-XPTO\": \"S\"}, {\"PROD-XPTO\": 39651, \"FAM-XPTO\": 6, \"CANAL-XPTO\": 5, \"GRUPO-XPTO\": 29, \"TAG-XPTO\": \"Y\", \"DATA-ATU-XPTO\": \"02.02.2018\", \"HORA-ATU-XPTO\": \"00:00:00\", \"ANL-ATU-XPTO\": \"352490021\", \"NOME-PROD-XPTO\": \"PERSONA VENICE MASTER BLASTER ITALIC\", \"DESC1-XPTO\": \"\", \"DESC2-XPTO\": \"\", \"DESC3-XPTO\": \"\", \"MSG-UPDATE-XPTO\": \"\", \"FLAG-XPTO\": \"S\"}, {\"PROD-XPTO\": 39965, \"FAM-XPTO\": 8, \"CANAL-XPTO\": 1, \"GRUPO-XPTO\": 71, \"TAG-XPTO\": \"Y\", \"DATA-ATU-XPTO\": \"13.08.2001\", \"HORA-ATU-XPTO\": \"00:00:00\", \"ANL-ATU-XPTO\": \"769270064\", \"NOME-PROD-XPTO\": \"CLASSIC CHOCO DELIGHT\", \"DESC1-XPTO\": \"\", \"DESC2-XPTO\": \"\", \"DESC3-XPTO\": \"\", \"MSG-UPDATE-XPTO\": \"\", \"FLAG-XPTO\": \"S\"}, {\"PROD-XPTO\": 40050, \"FAM-XPTO\": 6, \"CANAL-XPTO\": 1, \"GRUPO-XPTO\": 79, \"TAG-XPTO\": \"Y\", \"DATA-ATU-XPTO\": \"08.11.2005\", \"HORA-ATU-XPTO\": \"00:00:00\", \"ANL-ATU-XPTO\": \"726772127\", \"NOME-PROD-XPTO\": \"VANILLA ICE BLACK\", \"DESC1-XPTO\": \"\", \"DESC2-XPTO\": \"\", \"DESC3-XPTO\": \"\", \"MSG-UPDATE-XPTO\": \"\", \"FLAG-XPTO\": \"S\"}, {\"PROD-XPTO\": 41884, \"FAM-XPTO\": 5, \"CANAL-XPTO\": 4, \"GRUPO-XPTO\": 37, \"TAG-XPTO\": \"Z\", \"DATA-ATU-XPTO\": \"29.11.2012\", \"HORA-ATU-XPTO\": \"00:00:00\", \"ANL-ATU-XPTO\": \"854885116\", \"NOME-PROD-XPTO\": \"VANILLA ICE BLACK\", \"DESC1-XPTO\": \"\", \"DESC2-XPTO\": \"\", \"DESC3-XPTO\": \"\", \"MSG-UPDATE-XPTO\": \"\", \"FLAG-XPTO\": \"S\"}, {\"PROD-XPTO\": 42944, \"FAM-XPTO\": 2, \"CANAL-XPTO\": 4, \"GRUPO-XPTO\": 53, \"TAG-XPTO\": \"X\", \"DATA-ATU-XPTO\": \"16.12.2005\", \"HORA-ATU-XPTO\": \"00:00:00\", \"ANL-ATU-XPTO\": \"417779482\", \"NOME-PROD-XPTO\": \"PERSONA VENICE MASTER BLASTER ITALIC\", \"DESC1-XPTO\": \"\", \"DESC2-XPTO\": \"\", \"DESC3-XPTO\": \"\", \"MSG-UPDATE-XPTO\": \"\", \"FLAG-XPTO\": \"S\"}, {\"PROD-XPTO\": 46061, \"FAM-XPTO\": 8, \"CANAL-XPTO\": 2, \"GRUPO-XPTO\": 86, \"TAG-XPTO\": \"X\", \"DATA-ATU-XPTO\": \"21.09.2004\", \"HORA-ATU-XPTO\": \"00:00:00\", \"ANL-ATU-XPTO\": \"697529121\", \"NOME-PROD-XPTO\": \"GOLDEN SUNSET ELEGANCE\", \"DESC1-XPTO\": \"\", \"DESC2-XPTO\": \"\", \"DESC3-XPTO\": \"\", \"MSG-UPDATE-XPTO\": \"\", \"FLAG-XPTO\": \"S\"}, {\"PROD-XPTO\": 47296, \"FAM-XPTO\": 2, \"CANAL-XPTO\": 3, \"GRUPO-XPTO\": 65, \"TAG-XPTO\": \"X\", \"DATA-ATU-XPTO\": \"28.05.2019\", \"HORA-ATU-XPTO\": \"00:00:00\", \"ANL-ATU-XPTO\": \"869807044\", \"NOME-PROD-XPTO\": \"GOLDEN SUNSET ELEGANCE\", \"DESC1-XPTO\": \"\", \"DESC2-XPTO\": \"\", \"DESC3-XPTO\": \"\", \"MSG-UPDATE-XPTO\": \"\", \"FLAG-XPTO\": \"S\"}, {\"PROD-XPTO\": 47898, \"FAM-XPTO\": 9, \"CANAL-XPTO\": 5, \"GRUPO-XPTO\": 78, \"TAG-XPTO\": \"Y\", \"DATA-ATU-XPTO\": \"15.05.2010\", \"HORA-ATU-XPTO\": \"00:00:00\", \"ANL-ATU-XPTO\": \"647913695\", \"NOME-PROD-XPTO\": \"GOLDEN SUNSET ELEGANCE\", \"DESC1-XPTO\": \"\", \"DESC2-XPTO\": \"\", \"DESC3-XPTO\": \"\", \"MSG-UPDATE-XPTO\": \"\", \"FLAG-XPTO\": \"S\"}, {\"PROD-XPTO\": 48795, \"FAM-XPTO\": 1, \"CANAL-XPTO\": 1, \"GRUPO-XPTO\": 19, \"TAG-XPTO\": \"X\", \"DATA-ATU-XPTO\": \"08.01.2003\", \"HORA-ATU-XPTO\": \"00:00:00\", \"ANL-ATU-XPTO\": \"281466081\", \"NOME-PROD-XPTO\": \"VANILLA ICE BLACK\", \"DESC1-XPTO\": \"\", \"DESC2-XPTO\": \"\", \"DESC3-XPTO\": \"\", \"MSG-UPDATE-XPTO\": \"\", \"FLAG-XPTO\": \"S\"}, {\"PROD-XPTO\": 49392, \"FAM-XPTO\": 8, \"CANAL-XPTO\": 4, \"GRUPO-XPTO\": 73, \"TAG-XPTO\": \"Z\", \"DATA-ATU-XPTO\": \"20.04.2002\", \"HORA-ATU-XPTO\": \"00:00:00\", \"ANL-ATU-XPTO\": \"625743669\", \"NOME-PROD-XPTO\": \"GOLDEN SUNSET ELEGANCE\", \"DESC1-XPTO\": \"\", \"DESC2-XPTO\": \"\", \"DESC3-XPTO\": \"\", \"MSG-UPDATE-XPTO\": \"\", \"FLAG-XPTO\": \"S\"}, {\"PROD-XPTO\": 50238, \"FAM-XPTO\": 3, \"CANAL-XPTO\": 3, \"GRUPO-XPTO\": 35, \"TAG-XPTO\": \"Z\", \"DATA-ATU-XPTO\": \"17.04.2003\", \"HORA-ATU-XPTO\": \"00:00:00\", \"ANL-ATU-XPTO\": \"157107525\", \"NOME-PROD-XPTO\": \"NIGHT SHADOW SILVER\", \"DESC1-XPTO\": \"\", \"DESC2-XPTO\": \"\", \"DESC3-XPTO\": \"\", \"MSG-UPDATE-XPTO\": \"\", \"FLAG-XPTO\": \"S\"}, {\"PROD-XPTO\": 52311, \"FAM-XPTO\": 2, \"CANAL-XPTO\": 0, \"GRUPO-XPTO\": 30, \"TAG-XPTO\": \"X\", \"DATA-ATU-XPTO\": \"04.07.2023\", \"HORA-ATU-XPTO\": \"00:00:00\", \"ANL-ATU-XPTO\": \"491855689\", \"NOME-PROD-XPTO\": \"PERSONA VENICE MASTER BLASTER ITALIC\", \"DESC1-XPTO\": \"\", \"DESC2-XPTO\": \"\", \"DESC3-XPTO\": \"\", \"MSG-UPDATE-XPTO\": \"\", \"FLAG-XPTO\": \"S\"}, {\"PROD-XPTO\": 52771, \"FAM-XPTO\": 8, \"CANAL-XPTO\": 3, \"GRUPO-XPTO\": 10, \"TAG-XPTO\": \"Y\", \"DATA-ATU-XPTO\": \"08.02.2015\", \"HORA-ATU-XPTO\": \"00:00:00\", \"ANL-ATU-XPTO\": \"583138151\", \"NOME-PROD-XPTO\": \"MOCHA CARAMEL TWIST\", \"DESC1-XPTO\": \"\", \"DESC2-XPTO\": \"\", \"DESC3-XPTO\": \"\", \"MSG-UPDATE-XPTO\": \"\", \"FLAG-XPTO\": \"S\"}, {\"PROD-XPTO\": 53363, \"FAM-XPTO\": 10, \"CANAL-XPTO\": 3, \"GRUPO-XPTO\": 55, \"TAG-XPTO\": \"Y\", \"DATA-ATU-XPTO\": \"22.06.2004\", \"HORA-ATU-XPTO\": \"00:00:00\", \"ANL-ATU-XPTO\": \"565071523\", \"NOME-PROD-XPTO\": \"GOLDEN SUNSET ELEGANCE\", \"DESC1-XPTO\": \"\", \"DESC2-XPTO\": \"\", \"DESC3-XPTO\": \"\", \"MSG-UPDATE-XPTO\": \"\", \"FLAG-XPTO\": \"S\"}, {\"PROD-XPTO\": 53405, \"FAM-XPTO\": 7, \"CANAL-XPTO\": 4, \"GRUPO-XPTO\": 49, \"TAG-XPTO\": \"X\", \"DATA-ATU-XPTO\": \"14.05.2021\", \"HORA-ATU-XPTO\": \"00:00:00\", \"ANL-ATU-XPTO\": \"504534829\", \"NOME-PROD-XPTO\": \"NIGHT SHADOW SILVER\", \"DESC1-XPTO\": \"\", \"DESC2-XPTO\": \"\", \"DESC3-XPTO\": \"\", \"MSG-UPDATE-XPTO\": \"\", \"FLAG-XPTO\": \"S\"}, {\"PROD-XPTO\": 54335, \"FAM-XPTO\": 2, \"CANAL-XPTO\": 0, \"GRUPO-XPTO\": 82, \"TAG-XPTO\": \"X\", \"DATA-ATU-XPTO\": \"07.05.2018\", \"HORA-ATU-XPTO\": \"00:00:00\", \"ANL-ATU-XPTO\": \"962806828\", \"NOME-PROD-XPTO\": \"NIGHT SHADOW SILVER\", \"DESC1-XPTO\": \"\", \"DESC2-XPTO\": \"\", \"DESC3-XPTO\": \"\", \"MSG-UPDATE-XPTO\": \"\", \"FLAG-XPTO\": \"S\"}, {\"PROD-XPTO\": 55398, \"FAM-XPTO\": 6, \"CANAL-XPTO\": 3, \"GRUPO-XPTO\": 85, \"TAG-XPTO\": \"Y\", \"DATA-ATU-XPTO\": \"17.01.2009\", \"HORA-ATU-XPTO\": \"00:00:00\", \"ANL-ATU-XPTO\": \"303144348\", \"NOME-PROD-XPTO\": \"NIGHT SHADOW SILVER\", \"DESC1-XPTO\": \"\", \"DESC2-XPTO\": \"\", \"DESC3-XPTO\": \"\", \"MSG-UPDATE-XPTO\": \"\", \"FLAG-XPTO\": \"S\"}, {\"PROD-XPTO\": 56651, \"FAM-XPTO\": 3, \"CANAL-XPTO\": 1, \"GRUPO-XPTO\": 45, \"TAG-XPTO\": \"Z\", \"DATA-ATU-XPTO\": \"09.01.2006\", \"HORA-ATU-XPTO\": \"00:00:00\", \"ANL-ATU-XPTO\": \"713390425\", \"NOME-PROD-XPTO\": \"PERSONA VENICE MASTER BLASTER ITALIC\", \"DESC1-XPTO\": \"\", \"DESC2-XPTO\": \"\", \"DESC3-XPTO\": \"\", \"MSG-UPDATE-XPTO\": \"\", \"FLAG-XPTO\": \"S\"}, {\"PROD-XPTO\": 56770, \"FAM-XPTO\": 3, \"CANAL-XPTO\": 0, \"GRUPO-XPTO\": 83, \"TAG-XPTO\": \"Z\", \"DATA-ATU-XPTO\": \"17.08.2011\", \"HORA-ATU-XPTO\": \"00:00:00\", \"ANL-ATU-XPTO\": \"967087091\", \"NOME-PROD-XPTO\": \"MOCHA CARAMEL TWIST\", \"DESC1-XPTO\": \"\", \"DESC2-XPTO\": \"\", \"DESC3-XPTO\": \"\", \"MSG-UPDATE-XPTO\": \"\", \"FLAG-XPTO\": \"S\"}, {\"PROD-XPTO\": 57042, \"FAM-XPTO\": 3, \"CANAL-XPTO\": 1, \"GRUPO-XPTO\": 27, \"TAG-XPTO\": \"X\", \"DATA-ATU-XPTO\": \"30.05.2020\", \"HORA-ATU-XPTO\": \"00:00:00\", \"ANL-ATU-XPTO\": \"689227639\", \"NOME-PROD-XPTO\": \"GOLDEN SUNSET ELEGANCE\", \"DESC1-XPTO\": \"\", \"DESC2-XPTO\": \"\", \"DESC3-XPTO\": \"\", \"MSG-UPDATE-XPTO\": \"\", \"FLAG-XPTO\": \"S\"}, {\"PROD-XPTO\": 59932, \"FAM-XPTO\": 9, \"CANAL-XPTO\": 0, \"GRUPO-XPTO\": 83, \"TAG-XPTO\": \"Z\", \"DATA-ATU-XPTO\": \"09.10.2011\", \"HORA-ATU-XPTO\": \"00:00:00\", \"ANL-ATU-XPTO\": \"303808512\", \"NOME-PROD-XPTO\": \"VANILLA ICE BLACK\", \"DESC1-XPTO\": \"\", \"DESC2-XPTO\": \"\", \"DESC3-XPTO\": \"\", \"MSG-UPDATE-XPTO\": \"\", \"FLAG-XPTO\": \"S\"}, {\"PROD-XPTO\": 60666, \"FAM-XPTO\": 6, \"CANAL-XPTO\": 4, \"GRUPO-XPTO\": 22, \"TAG-XPTO\": \"Y\", \"DATA-ATU-XPTO\": \"03.05.2018\", \"HORA-ATU-XPTO\": \"00:00:00\", \"ANL-ATU-XPTO\": \"161970322\", \"NOME-PROD-XPTO\": \"NIGHT SHADOW SILVER\", \"DESC1-XPTO\": \"\", \"DESC2-XPTO\": \"\", \"DESC3-XPTO\": \"\", \"MSG-UPDATE-XPTO\": \"\", \"FLAG-XPTO\": \"S\"}, {\"PROD-XPTO\": 61684, \"FAM-XPTO\": 8, \"CANAL-XPTO\": 0, \"GRUPO-XPTO\": 29, \"TAG-XPTO\": \"X\", \"DATA-ATU-XPTO\": \"05.03.2014\", \"HORA-ATU-XPTO\": \"00:00:00\", \"ANL-ATU-XPTO\": \"815712758\", \"NOME-PROD-XPTO\": \"CLASSIC CHOCO DELIGHT\", \"DESC1-XPTO\": \"\", \"DESC2-XPTO\": \"\", \"DESC3-XPTO\": \"\", \"MSG-UPDATE-XPTO\": \"\", \"FLAG-XPTO\": \"S\"}, {\"PROD-XPTO\": 63501, \"FAM-XPTO\": 7, \"CANAL-XPTO\": 4, \"GRUPO-XPTO\": 31, \"TAG-XPTO\": \"X\", \"DATA-ATU-XPTO\": \"20.09.2009\", \"HORA-ATU-XPTO\": \"00:00:00\", \"ANL-ATU-XPTO\": \"788584713\", \"NOME-PROD-XPTO\": \"MOCHA CARAMEL TWIST\", \"DESC1-XPTO\": \"\", \"DESC2-XPTO\": \"\", \"DESC3-XPTO\": \"\", \"MSG-UPDATE-XPTO\": \"\", \"FLAG-XPTO\": \"S\"}, {\"PROD-XPTO\": 66072, \"FAM-XPTO\": 2, \"CANAL-XPTO\": 5, \"GRUPO-XPTO\": 74, \"TAG-XPTO\": \"Y\", \"DATA-ATU-XPTO\": \"22.03.2017\", \"HORA-ATU-XPTO\": \"00:00:00\", \"ANL-ATU-XPTO\": \"600804016\", \"NOME-PROD-XPTO\": \"MOCHA CARAMEL TWIST\", \"DESC1-XPTO\": \"\", \"DESC2-XPTO\": \"\", \"DESC3-XPTO\": \"\", \"MSG-UPDATE-XPTO\": \"\", \"FLAG-XPTO\": \"S\"}, {\"PROD-XPTO\": 66179, \"FAM-XPTO\": 4, \"CANAL-XPTO\": 1, \"GRUPO-XPTO\": 56, \"TAG-XPTO\": \"Z\", \"DATA-ATU-XPTO\": \"18.12.2010\", \"HORA-ATU-XPTO\": \"00:00:00\", \"ANL-ATU-XPTO\": \"551409901\", \"NOME-PROD-XPTO\": \"VANILLA ICE BLACK\", \"DESC1-XPTO\": \"\", \"DESC2-XPTO\": \"\", \"DESC3-XPTO\": \"\", \"MSG-UPDATE-XPTO\": \"\", \"FLAG-XPTO\": \"S\"}, {\"PROD-XPTO\": 66472, \"FAM-XPTO\": 4, \"CANAL-XPTO\": 4, \"GRUPO-XPTO\": 11, \"TAG-XPTO\": \"Z\", \"DATA-ATU-XPTO\": \"10.09.2000\", \"HORA-ATU-XPTO\": \"00:00:00\", \"ANL-ATU-XPTO\": \"525935402\", \"NOME-PROD-XPTO\": \"VANILLA ICE BLACK\", \"DESC1-XPTO\": \"\", \"DESC2-XPTO\": \"\", \"DESC3-XPTO\": \"\", \"MSG-UPDATE-XPTO\": \"\", \"FLAG-XPTO\": \"S\"}, {\"PROD-XPTO\": 67891, \"FAM-XPTO\": 1, \"CANAL-XPTO\": 2, \"GRUPO-XPTO\": 51, \"TAG-XPTO\": \"Y\", \"DATA-ATU-XPTO\": \"26.04.2022\", \"HORA-ATU-XPTO\": \"00:00:00\", \"ANL-ATU-XPTO\": \"304605493\", \"NOME-PROD-XPTO\": \"VANILLA ICE BLACK\", \"DESC1-XPTO\": \"\", \"DESC2-XPTO\": \"\", \"DESC3-XPTO\": \"\", \"MSG-UPDATE-XPTO\": \"\", \"FLAG-XPTO\": \"S\"}, {\"PROD-XPTO\": 67941, \"FAM-XPTO\": 3, \"CANAL-XPTO\": 3, \"GRUPO-XPTO\": 26, \"TAG-XPTO\": \"X\", \"DATA-ATU-XPTO\": \"16.05.2005\", \"HORA-ATU-XPTO\": \"00:00:00\", \"ANL-ATU-XPTO\": \"992169506\", \"NOME-PROD-XPTO\": \"MOCHA CARAMEL TWIST\", \"DESC1-XPTO\": \"\", \"DESC2-XPTO\": \"\", \"DESC3-XPTO\": \"\", \"MSG-UPDATE-XPTO\": \"\", \"FLAG-XPTO\": \"S\"}, {\"PROD-XPTO\": 68417, \"FAM-XPTO\": 9, \"CANAL-XPTO\": 1, \"GRUPO-XPTO\": 80, \"TAG-XPTO\": \"X\", \"DATA-ATU-XPTO\": \"09.12.2016\", \"HORA-ATU-XPTO\": \"00:00:00\", \"ANL-ATU-XPTO\": \"728929302\", \"NOME-PROD-XPTO\": \"PERSONA VENICE MASTER BLASTER ITALIC\", \"DESC1-XPTO\": \"\", \"DESC2-XPTO\": \"\", \"DESC3-XPTO\": \"\", \"MSG-UPDATE-XPTO\": \"\", \"FLAG-XPTO\": \"S\"}, {\"PROD-XPTO\": 68473, \"FAM-XPTO\": 6, \"CANAL-XPTO\": 5, \"GRUPO-XPTO\": 50, \"TAG-XPTO\": \"Z\", \"DATA-ATU-XPTO\": \"16.09.2018\", \"HORA-ATU-XPTO\": \"00:00:00\", \"ANL-ATU-XPTO\": \"234291229\", \"NOME-PROD-XPTO\": \"PERSONA VENICE MASTER BLASTER ITALIC\", \"DESC1-XPTO\": \"\", \"DESC2-XPTO\": \"\", \"DESC3-XPTO\": \"\", \"MSG-UPDATE-XPTO\": \"\", \"FLAG-XPTO\": \"S\"}, {\"PROD-XPTO\": 70587, \"FAM-XPTO\": 6, \"CANAL-XPTO\": 0, \"GRUPO-XPTO\": 56, \"TAG-XPTO\": \"Z\", \"DATA-ATU-XPTO\": \"16.10.2023\", \"HORA-ATU-XPTO\": \"00:00:00\", \"ANL-ATU-XPTO\": \"665989111\", \"NOME-PROD-XPTO\": \"MOCHA CARAMEL TWIST\", \"DESC1-XPTO\": \"\", \"DESC2-XPTO\": \"\", \"DESC3-XPTO\": \"\", \"MSG-UPDATE-XPTO\": \"\", \"FLAG-XPTO\": \"S\"}, {\"PROD-XPTO\": 70835, \"FAM-XPTO\": 8, \"CANAL-XPTO\": 1, \"GRUPO-XPTO\": 50, \"TAG-XPTO\": \"Z\", \"DATA-ATU-XPTO\": \"15.12.2000\", \"HORA-ATU-XPTO\": \"00:00:00\", \"ANL-ATU-XPTO\": \"959321584\", \"NOME-PROD-XPTO\": \"VANILLA ICE BLACK\", \"DESC1-XPTO\": \"\", \"DESC2-XPTO\": \"\", \"DESC3-XPTO\": \"\", \"MSG-UPDATE-XPTO\": \"\", \"FLAG-XPTO\": \"S\"}, {\"PROD-XPTO\": 71752, \"FAM-XPTO\": 7, \"CANAL-XPTO\": 0, \"GRUPO-XPTO\": 82, \"TAG-XPTO\": \"Z\", \"DATA-ATU-XPTO\": \"21.12.2018\", \"HORA-ATU-XPTO\": \"00:00:00\", \"ANL-ATU-XPTO\": \"794688995\", \"NOME-PROD-XPTO\": \"CLASSIC CHOCO DELIGHT\", \"DESC1-XPTO\": \"\", \"DESC2-XPTO\": \"\", \"DESC3-XPTO\": \"\", \"MSG-UPDATE-XPTO\": \"\", \"FLAG-XPTO\": \"S\"}, {\"PROD-XPTO\": 72415, \"FAM-XPTO\": 8, \"CANAL-XPTO\": 4, \"GRUPO-XPTO\": 55, \"TAG-XPTO\": \"Y\", \"DATA-ATU-XPTO\": \"04.03.2002\", \"HORA-ATU-XPTO\": \"00:00:00\", \"ANL-ATU-XPTO\": \"692196276\", \"NOME-PROD-XPTO\": \"MOCHA CARAMEL TWIST\", \"DESC1-XPTO\": \"\", \"DESC2-XPTO\": \"\", \"DESC3-XPTO\": \"\", \"MSG-UPDATE-XPTO\": \"\", \"FLAG-XPTO\": \"S\"}, {\"PROD-XPTO\": 73245, \"FAM-XPTO\": 1, \"CANAL-XPTO\": 4, \"GRUPO-XPTO\": 67, \"TAG-XPTO\": \"X\", \"DATA-ATU-XPTO\": \"22.08.2019\", \"HORA-ATU-XPTO\": \"00:00:00\", \"ANL-ATU-XPTO\": \"775282485\", \"NOME-PROD-XPTO\": \"VANILLA ICE BLACK\", \"DESC1-XPTO\": \"\", \"DESC2-XPTO\": \"\", \"DESC3-XPTO\": \"\", \"MSG-UPDATE-XPTO\": \"\", \"FLAG-XPTO\": \"S\"}, {\"PROD-XPTO\": 73393, \"FAM-XPTO\": 8, \"CANAL-XPTO\": 0, \"GRUPO-XPTO\": 69, \"TAG-XPTO\": \"Y\", \"DATA-ATU-XPTO\": \"17.03.2003\", \"HORA-ATU-XPTO\": \"00:00:00\", \"ANL-ATU-XPTO\": \"457577362\", \"NOME-PROD-XPTO\": \"GOLDEN SUNSET ELEGANCE\", \"DESC1-XPTO\": \"\", \"DESC2-XPTO\": \"\", \"DESC3-XPTO\": \"\", \"MSG-UPDATE-XPTO\": \"\", \"FLAG-XPTO\": \"S\"}, {\"PROD-XPTO\": 73811, \"FAM-XPTO\": 6, \"CANAL-XPTO\": 5, \"GRUPO-XPTO\": 43, \"TAG-XPTO\": \"X\", \"DATA-ATU-XPTO\": \"16.12.2022\", \"HORA-ATU-XPTO\": \"00:00:00\", \"ANL-ATU-XPTO\": \"784821245\", \"NOME-PROD-XPTO\": \"VANILLA ICE BLACK\", \"DESC1-XPTO\": \"\", \"DESC2-XPTO\": \"\", \"DESC3-XPTO\": \"\", \"MSG-UPDATE-XPTO\": \"\", \"FLAG-XPTO\": \"S\"}, {\"PROD-XPTO\": 74057, \"FAM-XPTO\": 3, \"CANAL-XPTO\": 1, \"GRUPO-XPTO\": 44, \"TAG-XPTO\": \"Z\", \"DATA-ATU-XPTO\": \"11.02.2001\", \"HORA-ATU-XPTO\": \"00:00:00\", \"ANL-ATU-XPTO\": \"377401764\", \"NOME-PROD-XPTO\": \"GOLDEN SUNSET ELEGANCE\", \"DESC1-XPTO\": \"\", \"DESC2-XPTO\": \"\", \"DESC3-XPTO\": \"\", \"MSG-UPDATE-XPTO\": \"\", \"FLAG-XPTO\": \"S\"}, {\"PROD-XPTO\": 75961, \"FAM-XPTO\": 1, \"CANAL-XPTO\": 1, \"GRUPO-XPTO\": 45, \"TAG-XPTO\": \"Z\", \"DATA-ATU-XPTO\": \"12.06.2005\", \"HORA-ATU-XPTO\": \"00:00:00\", \"ANL-ATU-XPTO\": \"127142066\", \"NOME-PROD-XPTO\": \"PERSONA VENICE MASTER BLASTER ITALIC\", \"DESC1-XPTO\": \"\", \"DESC2-XPTO\": \"\", \"DESC3-XPTO\": \"\", \"MSG-UPDATE-XPTO\": \"\", \"FLAG-XPTO\": \"S\"}, {\"PROD-XPTO\": 76019, \"FAM-XPTO\": 7, \"CANAL-XPTO\": 5, \"GRUPO-XPTO\": 85, \"TAG-XPTO\": \"X\", \"DATA-ATU-XPTO\": \"20.02.2008\", \"HORA-ATU-XPTO\": \"00:00:00\", \"ANL-ATU-XPTO\": \"898025873\", \"NOME-PROD-XPTO\": \"NIGHT SHADOW SILVER\", \"DESC1-XPTO\": \"\", \"DESC2-XPTO\": \"\", \"DESC3-XPTO\": \"\", \"MSG-UPDATE-XPTO\": \"\", \"FLAG-XPTO\": \"S\"}, {\"PROD-XPTO\": 76417, \"FAM-XPTO\": 2, \"CANAL-XPTO\": 3, \"GRUPO-XPTO\": 34, \"TAG-XPTO\": \"X\", \"DATA-ATU-XPTO\": \"21.12.2006\", \"HORA-ATU-XPTO\": \"00:00:00\", \"ANL-ATU-XPTO\": \"452698803\", \"NOME-PROD-XPTO\": \"VANILLA ICE BLACK\", \"DESC1-XPTO\": \"\", \"DESC2-XPTO\": \"\", \"DESC3-XPTO\": \"\", \"MSG-UPDATE-XPTO\": \"\", \"FLAG-XPTO\": \"S\"}, {\"PROD-XPTO\": 77484, \"FAM-XPTO\": 9, \"CANAL-XPTO\": 3, \"GRUPO-XPTO\": 25, \"TAG-XPTO\": \"Z\", \"DATA-ATU-XPTO\": \"05.12.2005\", \"HORA-ATU-XPTO\": \"00:00:00\", \"ANL-ATU-XPTO\": \"980116817\", \"NOME-PROD-XPTO\": \"NIGHT SHADOW SILVER\", \"DESC1-XPTO\": \"\", \"DESC2-XPTO\": \"\", \"DESC3-XPTO\": \"\", \"MSG-UPDATE-XPTO\": \"\", \"FLAG-XPTO\": \"S\"}, {\"PROD-XPTO\": 79496, \"FAM-XPTO\": 7, \"CANAL-XPTO\": 3, \"GRUPO-XPTO\": 69, \"TAG-XPTO\": \"Z\", \"DATA-ATU-XPTO\": \"11.11.2006\", \"HORA-ATU-XPTO\": \"00:00:00\", \"ANL-ATU-XPTO\": \"201809932\", \"NOME-PROD-XPTO\": \"MOCHA CARAMEL TWIST\", \"DESC1-XPTO\": \"\", \"DESC2-XPTO\": \"\", \"DESC3-XPTO\": \"\", \"MSG-UPDATE-XPTO\": \"\", \"FLAG-XPTO\": \"S\"}, {\"PROD-XPTO\": 79546, \"FAM-XPTO\": 1, \"CANAL-XPTO\": 0, \"GRUPO-XPTO\": 43, \"TAG-XPTO\": \"X\", \"DATA-ATU-XPTO\": \"17.09.2006\", \"HORA-ATU-XPTO\": \"00:00:00\", \"ANL-ATU-XPTO\": \"433318729\", \"NOME-PROD-XPTO\": \"CLASSIC CHOCO DELIGHT\", \"DESC1-XPTO\": \"\", \"DESC2-XPTO\": \"\", \"DESC3-XPTO\": \"\", \"MSG-UPDATE-XPTO\": \"\", \"FLAG-XPTO\": \"S\"}, {\"PROD-XPTO\": 79868, \"FAM-XPTO\": 1, \"CANAL-XPTO\": 5, \"GRUPO-XPTO\": 12, \"TAG-XPTO\": \"X\", \"DATA-ATU-XPTO\": \"12.12.2012\", \"HORA-ATU-XPTO\": \"00:00:00\", \"ANL-ATU-XPTO\": \"739997489\", \"NOME-PROD-XPTO\": \"CLASSIC CHOCO DELIGHT\", \"DESC1-XPTO\": \"\", \"DESC2-XPTO\": \"\", \"DESC3-XPTO\": \"\", \"MSG-UPDATE-XPTO\": \"\", \"FLAG-XPTO\": \"S\"}, {\"PROD-XPTO\": 80472, \"FAM-XPTO\": 9, \"CANAL-XPTO\": 0, \"GRUPO-XPTO\": 46, \"TAG-XPTO\": \"Z\", \"DATA-ATU-XPTO\": \"25.10.2001\", \"HORA-ATU-XPTO\": \"00:00:00\", \"ANL-ATU-XPTO\": \"281914005\", \"NOME-PROD-XPTO\": \"VANILLA ICE BLACK\", \"DESC1-XPTO\": \"\", \"DESC2-XPTO\": \"\", \"DESC3-XPTO\": \"\", \"MSG-UPDATE-XPTO\": \"\", \"FLAG-XPTO\": \"S\"}, {\"PROD-XPTO\": 81007, \"FAM-XPTO\": 4, \"CANAL-XPTO\": 2, \"GRUPO-XPTO\": 90, \"TAG-XPTO\": \"Y\", \"DATA-ATU-XPTO\": \"28.05.2018\", \"HORA-ATU-XPTO\": \"00:00:00\", \"ANL-ATU-XPTO\": \"419841935\", \"NOME-PROD-XPTO\": \"PERSONA VENICE MASTER BLASTER ITALIC\", \"DESC1-XPTO\": \"\", \"DESC2-XPTO\": \"\", \"DESC3-XPTO\": \"\", \"MSG-UPDATE-XPTO\": \"\", \"FLAG-XPTO\": \"S\"}, {\"PROD-XPTO\": 82275, \"FAM-XPTO\": 7, \"CANAL-XPTO\": 0, \"GRUPO-XPTO\": 29, \"TAG-XPTO\": \"X\", \"DATA-ATU-XPTO\": \"01.01.2020\", \"HORA-ATU-XPTO\": \"00:00:00\", \"ANL-ATU-XPTO\": \"971916050\", \"NOME-PROD-XPTO\": \"PERSONA VENICE MASTER BLASTER ITALIC\", \"DESC1-XPTO\": \"\", \"DESC2-XPTO\": \"\", \"DESC3-XPTO\": \"\", \"MSG-UPDATE-XPTO\": \"\", \"FLAG-XPTO\": \"S\"}, {\"PROD-XPTO\": 82556, \"FAM-XPTO\": 7, \"CANAL-XPTO\": 3, \"GRUPO-XPTO\": 70, \"TAG-XPTO\": \"Z\", \"DATA-ATU-XPTO\": \"12.10.2003\", \"HORA-ATU-XPTO\": \"00:00:00\", \"ANL-ATU-XPTO\": \"703782702\", \"NOME-PROD-XPTO\": \"CLASSIC CHOCO DELIGHT\", \"DESC1-XPTO\": \"\", \"DESC2-XPTO\": \"\", \"DESC3-XPTO\": \"\", \"MSG-UPDATE-XPTO\": \"\", \"FLAG-XPTO\": \"S\"}, {\"PROD-XPTO\": 82644, \"FAM-XPTO\": 5, \"CANAL-XPTO\": 5, \"GRUPO-XPTO\": 43, \"TAG-XPTO\": \"Y\", \"DATA-ATU-XPTO\": \"06.12.2004\", \"HORA-ATU-XPTO\": \"00:00:00\", \"ANL-ATU-XPTO\": \"156463147\", \"NOME-PROD-XPTO\": \"PERSONA VENICE MASTER BLASTER ITALIC\", \"DESC1-XPTO\": \"\", \"DESC2-XPTO\": \"\", \"DESC3-XPTO\": \"\", \"MSG-UPDATE-XPTO\": \"\", \"FLAG-XPTO\": \"S\"}, {\"PROD-XPTO\": 82943, \"FAM-XPTO\": 10, \"CANAL-XPTO\": 5, \"GRUPO-XPTO\": 25, \"TAG-XPTO\": \"Y\", \"DATA-ATU-XPTO\": \"29.07.2018\", \"HORA-ATU-XPTO\": \"00:00:00\", \"ANL-ATU-XPTO\": \"547170557\", \"NOME-PROD-XPTO\": \"GOLDEN SUNSET ELEGANCE\", \"DESC1-XPTO\": \"\", \"DESC2-XPTO\": \"\", \"DESC3-XPTO\": \"\", \"MSG-UPDATE-XPTO\": \"\", \"FLAG-XPTO\": \"S\"}, {\"PROD-XPTO\": 84477, \"FAM-XPTO\": 5, \"CANAL-XPTO\": 4, \"GRUPO-XPTO\": 98, \"TAG-XPTO\": \"X\", \"DATA-ATU-XPTO\": \"28.05.2010\", \"HORA-ATU-XPTO\": \"00:00:00\", \"ANL-ATU-XPTO\": \"895814301\", \"NOME-PROD-XPTO\": \"PERSONA VENICE MASTER BLASTER ITALIC\", \"DESC1-XPTO\": \"\", \"DESC2-XPTO\": \"\", \"DESC3-XPTO\": \"\", \"MSG-UPDATE-XPTO\": \"\", \"FLAG-XPTO\": \"S\"}, {\"PROD-XPTO\": 86856, \"FAM-XPTO\": 2, \"CANAL-XPTO\": 4, \"GRUPO-XPTO\": 23, \"TAG-XPTO\": \"Y\", \"DATA-ATU-XPTO\": \"06.02.2002\", \"HORA-ATU-XPTO\": \"00:00:00\", \"ANL-ATU-XPTO\": \"400549575\", \"NOME-PROD-XPTO\": \"CLASSIC CHOCO DELIGHT\", \"DESC1-XPTO\": \"\", \"DESC2-XPTO\": \"\", \"DESC3-XPTO\": \"\", \"MSG-UPDATE-XPTO\": \"\", \"FLAG-XPTO\": \"S\"}, {\"PROD-XPTO\": 87395, \"FAM-XPTO\": 6, \"CANAL-XPTO\": 2, \"GRUPO-XPTO\": 58, \"TAG-XPTO\": \"X\", \"DATA-ATU-XPTO\": \"30.04.2001\", \"HORA-ATU-XPTO\": \"00:00:00\", \"ANL-ATU-XPTO\": \"871687279\", \"NOME-PROD-XPTO\": \"CLASSIC CHOCO DELIGHT\", \"DESC1-XPTO\": \"\", \"DESC2-XPTO\": \"\", \"DESC3-XPTO\": \"\", \"MSG-UPDATE-XPTO\": \"\", \"FLAG-XPTO\": \"S\"}, {\"PROD-XPTO\": 87796, \"FAM-XPTO\": 10, \"CANAL-XPTO\": 2, \"GRUPO-XPTO\": 75, \"TAG-XPTO\": \"Z\", \"DATA-ATU-XPTO\": \"27.07.2004\", \"HORA-ATU-XPTO\": \"00:00:00\", \"ANL-ATU-XPTO\": \"335068501\", \"NOME-PROD-XPTO\": \"MOCHA CARAMEL TWIST\", \"DESC1-XPTO\": \"\", \"DESC2-XPTO\": \"\", \"DESC3-XPTO\": \"\", \"MSG-UPDATE-XPTO\": \"\", \"FLAG-XPTO\": \"S\"}, {\"PROD-XPTO\": 88130, \"FAM-XPTO\": 3, \"CANAL-XPTO\": 3, \"GRUPO-XPTO\": 96, \"TAG-XPTO\": \"Y\", \"DATA-ATU-XPTO\": \"21.03.2007\", \"HORA-ATU-XPTO\": \"00:00:00\", \"ANL-ATU-XPTO\": \"102773758\", \"NOME-PROD-XPTO\": \"GOLDEN SUNSET ELEGANCE\", \"DESC1-XPTO\": \"\", \"DESC2-XPTO\": \"\", \"DESC3-XPTO\": \"\", \"MSG-UPDATE-XPTO\": \"\", \"FLAG-XPTO\": \"S\"}, {\"PROD-XPTO\": 89634, \"FAM-XPTO\": 7, \"CANAL-XPTO\": 2, \"GRUPO-XPTO\": 83, \"TAG-XPTO\": \"Y\", \"DATA-ATU-XPTO\": \"12.03.2007\", \"HORA-ATU-XPTO\": \"00:00:00\", \"ANL-ATU-XPTO\": \"230548880\", \"NOME-PROD-XPTO\": \"VANILLA ICE BLACK\", \"DESC1-XPTO\": \"\", \"DESC2-XPTO\": \"\", \"DESC3-XPTO\": \"\", \"MSG-UPDATE-XPTO\": \"\", \"FLAG-XPTO\": \"S\"}, {\"PROD-XPTO\": 90040, \"FAM-XPTO\": 4, \"CANAL-XPTO\": 2, \"GRUPO-XPTO\": 58, \"TAG-XPTO\": \"Z\", \"DATA-ATU-XPTO\": \"26.12.2014\", \"HORA-ATU-XPTO\": \"00:00:00\", \"ANL-ATU-XPTO\": \"888244026\", \"NOME-PROD-XPTO\": \"PERSONA VENICE MASTER BLASTER ITALIC\", \"DESC1-XPTO\": \"\", \"DESC2-XPTO\": \"\", \"DESC3-XPTO\": \"\", \"MSG-UPDATE-XPTO\": \"\", \"FLAG-XPTO\": \"S\"}, {\"PROD-XPTO\": 90998, \"FAM-XPTO\": 10, \"CANAL-XPTO\": 3, \"GRUPO-XPTO\": 79, \"TAG-XPTO\": \"X\", \"DATA-ATU-XPTO\": \"20.08.2009\", \"HORA-ATU-XPTO\": \"00:00:00\", \"ANL-ATU-XPTO\": \"973730054\", \"NOME-PROD-XPTO\": \"NIGHT SHADOW SILVER\", \"DESC1-XPTO\": \"\", \"DESC2-XPTO\": \"\", \"DESC3-XPTO\": \"\", \"MSG-UPDATE-XPTO\": \"\", \"FLAG-XPTO\": \"S\"}, {\"PROD-XPTO\": 92404, \"FAM-XPTO\": 9, \"CANAL-XPTO\": 5, \"GRUPO-XPTO\": 74, \"TAG-XPTO\": \"X\", \"DATA-ATU-XPTO\": \"13.10.2022\", \"HORA-ATU-XPTO\": \"00:00:00\", \"ANL-ATU-XPTO\": \"749038171\", \"NOME-PROD-XPTO\": \"MOCHA CARAMEL TWIST\", \"DESC1-XPTO\": \"\", \"DESC2-XPTO\": \"\", \"DESC3-XPTO\": \"\", \"MSG-UPDATE-XPTO\": \"\", \"FLAG-XPTO\": \"S\"}, {\"PROD-XPTO\": 94432, \"FAM-XPTO\": 1, \"CANAL-XPTO\": 5, \"GRUPO-XPTO\": 47, \"TAG-XPTO\": \"Y\", \"DATA-ATU-XPTO\": \"15.11.2015\", \"HORA-ATU-XPTO\": \"00:00:00\", \"ANL-ATU-XPTO\": \"962912109\", \"NOME-PROD-XPTO\": \"VANILLA ICE BLACK\", \"DESC1-XPTO\": \"\", \"DESC2-XPTO\": \"\", \"DESC3-XPTO\": \"\", \"MSG-UPDATE-XPTO\": \"\", \"FLAG-XPTO\": \"S\"}, {\"PROD-XPTO\": 95043, \"FAM-XPTO\": 9, \"CANAL-XPTO\": 4, \"GRUPO-XPTO\": 55, \"TAG-XPTO\": \"Z\", \"DATA-ATU-XPTO\": \"24.10.2003\", \"HORA-ATU-XPTO\": \"00:00:00\", \"ANL-ATU-XPTO\": \"274407511\", \"NOME-PROD-XPTO\": \"CLASSIC CHOCO DELIGHT\", \"DESC1-XPTO\": \"\", \"DESC2-XPTO\": \"\", \"DESC3-XPTO\": \"\", \"MSG-UPDATE-XPTO\": \"\", \"FLAG-XPTO\": \"S\"}, {\"PROD-XPTO\": 95542, \"FAM-XPTO\": 3, \"CANAL-XPTO\": 4, \"GRUPO-XPTO\": 58, \"TAG-XPTO\": \"Y\", \"DATA-ATU-XPTO\": \"11.12.2009\", \"HORA-ATU-XPTO\": \"00:00:00\", \"ANL-ATU-XPTO\": \"592382299\", \"NOME-PROD-XPTO\": \"NIGHT SHADOW SILVER\", \"DESC1-XPTO\": \"\", \"DESC2-XPTO\": \"\", \"DESC3-XPTO\": \"\", \"MSG-UPDATE-XPTO\": \"\", \"FLAG-XPTO\": \"S\"}, {\"PROD-XPTO\": 97671, \"FAM-XPTO\": 7, \"CANAL-XPTO\": 3, \"GRUPO-XPTO\": 69, \"TAG-XPTO\": \"Y\", \"DATA-ATU-XPTO\": \"03.03.2009\", \"HORA-ATU-XPTO\": \"00:00:00\", \"ANL-ATU-XPTO\": \"763677252\", \"NOME-PROD-XPTO\": \"NIGHT SHADOW SILVER\", \"DESC1-XPTO\": \"\", \"DESC2-XPTO\": \"\", \"DESC3-XPTO\": \"\", \"MSG-UPDATE-XPTO\": \"\", \"FLAG-XPTO\": \"S\"}, {\"PROD-XPTO\": 97939, \"FAM-XPTO\": 8, \"CANAL-XPTO\": 5, \"GRUPO-XPTO\": 53, \"TAG-XPTO\": \"Z\", \"DATA-ATU-XPTO\": \"02.02.2005\", \"HORA-ATU-XPTO\": \"00:00:00\", \"ANL-ATU-XPTO\": \"939351350\", \"NOME-PROD-XPTO\": \"CLASSIC CHOCO DELIGHT\", \"DESC1-XPTO\": \"\", \"DESC2-XPTO\": \"\", \"DESC3-XPTO\": \"\", \"MSG-UPDATE-XPTO\": \"\", \"FLAG-XPTO\": \"S\"}, {\"PROD-XPTO\": 99317, \"FAM-XPTO\": 8, \"CANAL-XPTO\": 1, \"GRUPO-XPTO\": 83, \"TAG-XPTO\": \"X\", \"DATA-ATU-XPTO\": \"15.12.2013\", \"HORA-ATU-XPTO\": \"00:00:00\", \"ANL-ATU-XPTO\": \"282637514\", \"NOME-PROD-XPTO\": \"CLASSIC CHOCO DELIGHT\", \"DESC1-XPTO\": \"\", \"DESC2-XPTO\": \"\", \"DESC3-XPTO\": \"\", \"MSG-UPDATE-XPTO\": \"\", \"FLAG-XPTO\": \"S\"}, {\"PROD-XPTO\": 99566, \"FAM-XPTO\": 1, \"CANAL-XPTO\": 3, \"GRUPO-XPTO\": 90, \"TAG-XPTO\": \"Z\", \"DATA-ATU-XPTO\": \"30.10.2008\", \"HORA-ATU-XPTO\": \"00:00:00\", \"ANL-ATU-XPTO\": \"427527847\", \"NOME-PROD-XPTO\": \"CLASSIC CHOCO DELIGHT\", \"DESC1-XPTO\": \"\", \"DESC2-XPTO\": \"\", \"DESC3-XPTO\": \"\", \"MSG-UPDATE-XPTO\": \"\", \"FLAG-XPTO\": \"S\"}, {\"PROD-XPTO\": 99974, \"FAM-XPTO\": 5, \"CANAL-XPTO\": 3, \"GRUPO-XPTO\": 62, \"TAG-XPTO\": \"Y\", \"DATA-ATU-XPTO\": \"06.05.2022\", \"HORA-ATU-XPTO\": \"00:00:00\", \"ANL-ATU-XPTO\": \"634526665\", \"NOME-PROD-XPTO\": \"MOCHA CARAMEL TWIST\", \"DESC1-XPTO\": \"\", \"DESC2-XPTO\": \"\", \"DESC3-XPTO\": \"\", \"MSG-UPDATE-XPTO\": \"\", \"FLAG-XPTO\": \"S\"}]}, \"Server\": \"serv0123456\", \"Terminal\": \"\"}}"}